{
  "summary": {
    "totalFeatures": 9,
    "totalScenarios": 22,
    "passedScenarios": 21,
    "failedScenarios": 1,
    "skippedScenarios": 0,
    "totalSteps": 175,
    "passedSteps": 169,
    "failedSteps": 1,
    "skippedSteps": 5,
    "totalDuration": 403129678402,
    "totalDurationFormatted": "6m 43s",
    "averageScenarioDuration": "18.32s",
    "passRate": "95.45%"
  },
  "features": [
    {
      "name": "Login",
      "uri": "features/1-login.feature",
      "scenarios": [
        {
          "name": "Bob wants to login to ZAC",
          "type": "scenario",
          "status": "passed",
          "duration": 8281370957,
          "durationFormatted": "8.28s",
          "steps": 5,
          "tags": []
        },
        {
          "name": "Bob wants to log out of the application after being logged in",
          "type": "scenario",
          "status": "passed",
          "duration": 4606165453,
          "durationFormatted": "4.61s",
          "steps": 6,
          "tags": []
        },
        {
          "name": "Bob logs back in",
          "type": "scenario",
          "status": "passed",
          "duration": 4621939301,
          "durationFormatted": "4.62s",
          "steps": 6,
          "tags": []
        },
        {
          "name": "Bob wants to log out of the application after being logged in",
          "type": "scenario",
          "status": "passed",
          "duration": 4400229276,
          "durationFormatted": "4.40s",
          "steps": 6,
          "tags": []
        },
        {
          "name": "Bob logs back in",
          "type": "scenario",
          "status": "passed",
          "duration": 4811157420,
          "durationFormatted": "4.81s",
          "steps": 6,
          "tags": []
        }
      ],
      "totalDuration": 26720862407,
      "passedScenarios": 5,
      "failedScenarios": 0,
      "skippedScenarios": 0,
      "totalDurationFormatted": "26.72s"
    },
    {
      "name": "Zaken toevoegen",
      "uri": "features/2-zaken-toevoegen.feature",
      "scenarios": [
        {
          "name": "Bob wants to create a new zaak",
          "type": "scenario",
          "status": "passed",
          "duration": 44378139330,
          "durationFormatted": "44.38s",
          "steps": 9,
          "tags": []
        }
      ],
      "totalDuration": 44378139330,
      "passedScenarios": 1,
      "failedScenarios": 0,
      "skippedScenarios": 0,
      "totalDurationFormatted": "44.38s"
    },
    {
      "name": "Open Formulieren",
      "uri": "features/3-open-formulieren.feature",
      "scenarios": [
        {
          "name": "Resident fills in indienen-aansprakelijkheid-behandelen open-forms form",
          "type": "scenario",
          "status": "failed",
          "duration": 44939521238,
          "durationFormatted": "44.94s",
          "steps": 8,
          "tags": [
            "@live-env-only"
          ]
        }
      ],
      "totalDuration": 44939521238,
      "passedScenarios": 0,
      "failedScenarios": 1,
      "skippedScenarios": 0,
      "totalDurationFormatted": "44.94s"
    },
    {
      "name": "SmartDocuments",
      "uri": "features/4-smartdocuments.feature",
      "scenarios": [
        {
          "name": "Employee wants to create a new document for a zaak Using the SmartDocuments wizard",
          "type": "scenario",
          "status": "passed",
          "duration": 31136348933,
          "durationFormatted": "31.14s",
          "steps": 10,
          "tags": []
        }
      ],
      "totalDuration": 31136348933,
      "passedScenarios": 1,
      "failedScenarios": 0,
      "skippedScenarios": 0,
      "totalDurationFormatted": "31.14s"
    },
    {
      "name": "Taken toevoegen",
      "uri": "features/5-taken-toevoegen.feature",
      "scenarios": [
        {
          "name": "Employee \"Bob\" does not have enough information to finish Intake and assigns a task to Employee \"Oscar\"",
          "type": "scenario",
          "status": "passed",
          "duration": 26146441755,
          "durationFormatted": "26.15s",
          "steps": 10,
          "tags": []
        }
      ],
      "totalDuration": 26146441755,
      "passedScenarios": 1,
      "failedScenarios": 0,
      "skippedScenarios": 0,
      "totalDurationFormatted": "26.15s"
    },
    {
      "name": "Zaken verdelen / vrijgeven",
      "uri": "features/6-zaken-verdelen-vrijgeven.feature",
      "scenarios": [
        {
          "name": "Bob assigns zaken to a group and user from the list",
          "type": "scenario",
          "status": "passed",
          "duration": 11716458637,
          "durationFormatted": "11.72s",
          "steps": 10,
          "tags": []
        },
        {
          "name": "Bob releases zaken from the list",
          "type": "scenario",
          "status": "passed",
          "duration": 22402682723,
          "durationFormatted": "22.40s",
          "steps": 10,
          "tags": []
        }
      ],
      "totalDuration": 34119141360,
      "passedScenarios": 2,
      "failedScenarios": 0,
      "skippedScenarios": 0,
      "totalDurationFormatted": "34.12s"
    },
    {
      "name": "Taken verdelen / vrijgeven",
      "uri": "features/7-taken-verdelen-vrijgeven.feature",
      "scenarios": [
        {
          "name": "Bob assigns taken to a group and user from the list",
          "type": "scenario",
          "status": "passed",
          "duration": 10213951675,
          "durationFormatted": "10.21s",
          "steps": 10,
          "tags": []
        },
        {
          "name": "Bob releases taken",
          "type": "scenario",
          "status": "passed",
          "duration": 20236992202,
          "durationFormatted": "20.24s",
          "steps": 10,
          "tags": []
        }
      ],
      "totalDuration": 30450943877,
      "passedScenarios": 2,
      "failedScenarios": 0,
      "skippedScenarios": 0,
      "totalDurationFormatted": "30.45s"
    },
    {
      "name": "Personen",
      "uri": "features/8-personen.feature",
      "scenarios": [
        {
          "name": "Bob wants to view a person",
          "type": "scenario",
          "status": "passed",
          "duration": 29469858769,
          "durationFormatted": "29.47s",
          "steps": 6,
          "tags": []
        },
        {
          "name": "Bob inspects person details",
          "type": "scenario",
          "status": "passed",
          "duration": 11181603518,
          "durationFormatted": "11.18s",
          "steps": 6,
          "tags": []
        }
      ],
      "totalDuration": 40651462287,
      "passedScenarios": 2,
      "failedScenarios": 0,
      "skippedScenarios": 0,
      "totalDurationFormatted": "40.65s"
    },
    {
      "name": "BPMN",
      "uri": "features/9-bpmn.feature",
      "scenarios": [
        {
          "name": "Bob wants to create a new BPMN zaak",
          "type": "scenario",
          "status": "passed",
          "duration": 32376245161,
          "durationFormatted": "32.38s",
          "steps": 8,
          "tags": []
        },
        {
          "name": "Bob changes the assigned user and group",
          "type": "scenario",
          "status": "passed",
          "duration": 18125261172,
          "durationFormatted": "18.13s",
          "steps": 7,
          "tags": []
        },
        {
          "name": "Bob opens the initial task form",
          "type": "scenario",
          "status": "passed",
          "duration": 10930946444,
          "durationFormatted": "10.93s",
          "steps": 6,
          "tags": []
        },
        {
          "name": "Bob creates two SmartDocuments Word files",
          "type": "scenario",
          "status": "passed",
          "duration": 26859200745,
          "durationFormatted": "26.86s",
          "steps": 11,
          "tags": []
        },
        {
          "name": "Bob fills-in and submits the task form",
          "type": "scenario",
          "status": "passed",
          "duration": 15183627342,
          "durationFormatted": "15.18s",
          "steps": 11,
          "tags": []
        },
        {
          "name": "Bob inspects the summary task form",
          "type": "scenario",
          "status": "passed",
          "duration": 7431253760,
          "durationFormatted": "7.43s",
          "steps": 6,
          "tags": []
        },
        {
          "name": "Bob confirms the data in the summary form",
          "type": "scenario",
          "status": "passed",
          "duration": 13680282591,
          "durationFormatted": "13.68s",
          "steps": 8,
          "tags": []
        }
      ],
      "totalDuration": 124586817215,
      "passedScenarios": 7,
      "failedScenarios": 0,
      "skippedScenarios": 0,
      "totalDurationFormatted": "2m 4s"
    }
  ],
  "slowestScenarios": [
    {
      "feature": "Open Formulieren",
      "scenario": "Resident fills in indienen-aansprakelijkheid-behandelen open-forms form",
      "duration": 44939521238,
      "durationFormatted": "44.94s"
    },
    {
      "feature": "Zaken toevoegen",
      "scenario": "Bob wants to create a new zaak",
      "duration": 44378139330,
      "durationFormatted": "44.38s"
    },
    {
      "feature": "BPMN",
      "scenario": "Bob wants to create a new BPMN zaak",
      "duration": 32376245161,
      "durationFormatted": "32.38s"
    },
    {
      "feature": "SmartDocuments",
      "scenario": "Employee wants to create a new document for a zaak Using the SmartDocuments wizard",
      "duration": 31136348933,
      "durationFormatted": "31.14s"
    },
    {
      "feature": "Personen",
      "scenario": "Bob wants to view a person",
      "duration": 29469858769,
      "durationFormatted": "29.47s"
    },
    {
      "feature": "BPMN",
      "scenario": "Bob creates two SmartDocuments Word files",
      "duration": 26859200745,
      "durationFormatted": "26.86s"
    },
    {
      "feature": "Taken toevoegen",
      "scenario": "Employee \"Bob\" does not have enough information to finish Intake and assigns a task to Employee \"Oscar\"",
      "duration": 26146441755,
      "durationFormatted": "26.15s"
    },
    {
      "feature": "Zaken verdelen / vrijgeven",
      "scenario": "Bob releases zaken from the list",
      "duration": 22402682723,
      "durationFormatted": "22.40s"
    },
    {
      "feature": "Taken verdelen / vrijgeven",
      "scenario": "Bob releases taken",
      "duration": 20236992202,
      "durationFormatted": "20.24s"
    },
    {
      "feature": "BPMN",
      "scenario": "Bob changes the assigned user and group",
      "duration": 18125261172,
      "durationFormatted": "18.13s"
    }
  ],
  "failedScenarios": [
    {
      "feature": "Open Formulieren",
      "scenario": "Resident fills in indienen-aansprakelijkheid-behandelen open-forms form",
      "step": "Resident \"Alice\" fills in the indienen-aansprakelijkheid-behandelen open-forms form",
      "error": "locator.check: Timeout 30000ms exceeded.",
      "duration": "44.94s"
    }
  ],
  "timestamp": "2026-02-05T21:15:15.513Z"
}