{
  "summary": {
    "totalFeatures": 9,
    "totalScenarios": 22,
    "passedScenarios": 18,
    "failedScenarios": 4,
    "skippedScenarios": 0,
    "totalSteps": 175,
    "passedSteps": 164,
    "failedSteps": 4,
    "skippedSteps": 7,
    "totalDuration": 544449857018,
    "totalDurationFormatted": "9m 4s",
    "averageScenarioDuration": "24.75s",
    "passRate": "81.82%"
  },
  "features": [
    {
      "name": "Login",
      "uri": "features/1-login.feature",
      "scenarios": [
        {
          "name": "Bob wants to login to ZAC",
          "type": "scenario",
          "status": "passed",
          "duration": 9712918052,
          "durationFormatted": "9.71s",
          "steps": 5,
          "tags": []
        },
        {
          "name": "Bob wants to log out of the application after being logged in",
          "type": "scenario",
          "status": "passed",
          "duration": 6326407062,
          "durationFormatted": "6.33s",
          "steps": 6,
          "tags": []
        },
        {
          "name": "Bob logs back in",
          "type": "scenario",
          "status": "passed",
          "duration": 6067217229,
          "durationFormatted": "6.07s",
          "steps": 6,
          "tags": []
        },
        {
          "name": "Bob wants to log out of the application after being logged in",
          "type": "scenario",
          "status": "passed",
          "duration": 6292854490,
          "durationFormatted": "6.29s",
          "steps": 6,
          "tags": []
        },
        {
          "name": "Bob logs back in",
          "type": "scenario",
          "status": "passed",
          "duration": 5950573003,
          "durationFormatted": "5.95s",
          "steps": 6,
          "tags": []
        }
      ],
      "totalDuration": 34349969836,
      "passedScenarios": 5,
      "failedScenarios": 0,
      "skippedScenarios": 0,
      "totalDurationFormatted": "34.35s"
    },
    {
      "name": "Zaken toevoegen",
      "uri": "features/2-zaken-toevoegen.feature",
      "scenarios": [
        {
          "name": "Bob wants to create a new zaak",
          "type": "scenario",
          "status": "passed",
          "duration": 47832776490,
          "durationFormatted": "47.83s",
          "steps": 9,
          "tags": []
        }
      ],
      "totalDuration": 47832776490,
      "passedScenarios": 1,
      "failedScenarios": 0,
      "skippedScenarios": 0,
      "totalDurationFormatted": "47.83s"
    },
    {
      "name": "Open Formulieren",
      "uri": "features/3-open-formulieren.feature",
      "scenarios": [
        {
          "name": "Resident fills in indienen-aansprakelijkheid-behandelen open-forms form",
          "type": "scenario",
          "status": "passed",
          "duration": 53447424407,
          "durationFormatted": "53.45s",
          "steps": 8,
          "tags": [
            "@live-env-only"
          ]
        }
      ],
      "totalDuration": 53447424407,
      "passedScenarios": 1,
      "failedScenarios": 0,
      "skippedScenarios": 0,
      "totalDurationFormatted": "53.45s"
    },
    {
      "name": "SmartDocuments",
      "uri": "features/4-smartdocuments.feature",
      "scenarios": [
        {
          "name": "Employee wants to create a new document for a zaak Using the SmartDocuments wizard",
          "type": "scenario",
          "status": "passed",
          "duration": 33869046698,
          "durationFormatted": "33.87s",
          "steps": 10,
          "tags": []
        }
      ],
      "totalDuration": 33869046698,
      "passedScenarios": 1,
      "failedScenarios": 0,
      "skippedScenarios": 0,
      "totalDurationFormatted": "33.87s"
    },
    {
      "name": "Taken toevoegen",
      "uri": "features/5-taken-toevoegen.feature",
      "scenarios": [
        {
          "name": "Employee \"Bob\" does not have enough information to finish Intake and assigns a task to Employee \"Oscar\"",
          "type": "scenario",
          "status": "passed",
          "duration": 35830833761,
          "durationFormatted": "35.83s",
          "steps": 10,
          "tags": []
        }
      ],
      "totalDuration": 35830833761,
      "passedScenarios": 1,
      "failedScenarios": 0,
      "skippedScenarios": 0,
      "totalDurationFormatted": "35.83s"
    },
    {
      "name": "Zaken verdelen / vrijgeven",
      "uri": "features/6-zaken-verdelen-vrijgeven.feature",
      "scenarios": [
        {
          "name": "Bob assigns zaken to a group and user from the list",
          "type": "scenario",
          "status": "passed",
          "duration": 14435563160,
          "durationFormatted": "14.44s",
          "steps": 10,
          "tags": []
        },
        {
          "name": "Bob releases zaken from the list",
          "type": "scenario",
          "status": "passed",
          "duration": 25913394063,
          "durationFormatted": "25.91s",
          "steps": 10,
          "tags": []
        }
      ],
      "totalDuration": 40348957223,
      "passedScenarios": 2,
      "failedScenarios": 0,
      "skippedScenarios": 0,
      "totalDurationFormatted": "40.35s"
    },
    {
      "name": "Taken verdelen / vrijgeven",
      "uri": "features/7-taken-verdelen-vrijgeven.feature",
      "scenarios": [
        {
          "name": "Bob assigns taken to a group and user from the list",
          "type": "scenario",
          "status": "passed",
          "duration": 13908790817,
          "durationFormatted": "13.91s",
          "steps": 10,
          "tags": []
        },
        {
          "name": "Bob releases taken",
          "type": "scenario",
          "status": "passed",
          "duration": 23240122878,
          "durationFormatted": "23.24s",
          "steps": 10,
          "tags": []
        }
      ],
      "totalDuration": 37148913695,
      "passedScenarios": 2,
      "failedScenarios": 0,
      "skippedScenarios": 0,
      "totalDurationFormatted": "37.15s"
    },
    {
      "name": "Personen",
      "uri": "features/8-personen.feature",
      "scenarios": [
        {
          "name": "Bob wants to view a person",
          "type": "scenario",
          "status": "passed",
          "duration": 33404007684,
          "durationFormatted": "33.40s",
          "steps": 6,
          "tags": []
        },
        {
          "name": "Bob inspects person details",
          "type": "scenario",
          "status": "passed",
          "duration": 13065708966,
          "durationFormatted": "13.07s",
          "steps": 6,
          "tags": []
        }
      ],
      "totalDuration": 46469716650,
      "passedScenarios": 2,
      "failedScenarios": 0,
      "skippedScenarios": 0,
      "totalDurationFormatted": "46.47s"
    },
    {
      "name": "BPMN",
      "uri": "features/9-bpmn.feature",
      "scenarios": [
        {
          "name": "Bob wants to create a new BPMN zaak",
          "type": "scenario",
          "status": "passed",
          "duration": 37628161331,
          "durationFormatted": "37.63s",
          "steps": 8,
          "tags": []
        },
        {
          "name": "Bob changes the assigned user and group",
          "type": "scenario",
          "status": "failed",
          "duration": 21575461495,
          "durationFormatted": "21.58s",
          "steps": 7,
          "tags": []
        },
        {
          "name": "Bob opens the initial task form",
          "type": "scenario",
          "status": "passed",
          "duration": 14323896030,
          "durationFormatted": "14.32s",
          "steps": 6,
          "tags": []
        },
        {
          "name": "Bob creates two SmartDocuments Word files",
          "type": "scenario",
          "status": "passed",
          "duration": 35014738474,
          "durationFormatted": "35.01s",
          "steps": 11,
          "tags": []
        },
        {
          "name": "Bob fills-in and submits the task form",
          "type": "scenario",
          "status": "failed",
          "duration": 46182174447,
          "durationFormatted": "46.18s",
          "steps": 11,
          "tags": []
        },
        {
          "name": "Bob inspects the summary task form",
          "type": "scenario",
          "status": "failed",
          "duration": 17277859752,
          "durationFormatted": "17.28s",
          "steps": 6,
          "tags": []
        },
        {
          "name": "Bob confirms the data in the summary form",
          "type": "scenario",
          "status": "failed",
          "duration": 43149926729,
          "durationFormatted": "43.15s",
          "steps": 8,
          "tags": []
        }
      ],
      "totalDuration": 215152218258,
      "passedScenarios": 3,
      "failedScenarios": 4,
      "skippedScenarios": 0,
      "totalDurationFormatted": "3m 35s"
    }
  ],
  "slowestScenarios": [
    {
      "feature": "Open Formulieren",
      "scenario": "Resident fills in indienen-aansprakelijkheid-behandelen open-forms form",
      "duration": 53447424407,
      "durationFormatted": "53.45s"
    },
    {
      "feature": "Zaken toevoegen",
      "scenario": "Bob wants to create a new zaak",
      "duration": 47832776490,
      "durationFormatted": "47.83s"
    },
    {
      "feature": "BPMN",
      "scenario": "Bob fills-in and submits the task form",
      "duration": 46182174447,
      "durationFormatted": "46.18s"
    },
    {
      "feature": "BPMN",
      "scenario": "Bob confirms the data in the summary form",
      "duration": 43149926729,
      "durationFormatted": "43.15s"
    },
    {
      "feature": "BPMN",
      "scenario": "Bob wants to create a new BPMN zaak",
      "duration": 37628161331,
      "durationFormatted": "37.63s"
    },
    {
      "feature": "Taken toevoegen",
      "scenario": "Employee \"Bob\" does not have enough information to finish Intake and assigns a task to Employee \"Oscar\"",
      "duration": 35830833761,
      "durationFormatted": "35.83s"
    },
    {
      "feature": "BPMN",
      "scenario": "Bob creates two SmartDocuments Word files",
      "duration": 35014738474,
      "durationFormatted": "35.01s"
    },
    {
      "feature": "SmartDocuments",
      "scenario": "Employee wants to create a new document for a zaak Using the SmartDocuments wizard",
      "duration": 33869046698,
      "durationFormatted": "33.87s"
    },
    {
      "feature": "Personen",
      "scenario": "Bob wants to view a person",
      "duration": 33404007684,
      "durationFormatted": "33.40s"
    },
    {
      "feature": "Zaken verdelen / vrijgeven",
      "scenario": "Bob releases zaken from the list",
      "duration": 25913394063,
      "durationFormatted": "25.91s"
    }
  ],
  "failedScenarios": [
    {
      "feature": "BPMN",
      "scenario": "Bob changes the assigned user and group",
      "step": "\"Bob\" sees group \"Test groep B\" and user \"Test User2\" in the zaak data",
      "error": "Error: expect(locator).toHaveValue(expected) failed",
      "duration": "21.58s"
    },
    {
      "feature": "BPMN",
      "scenario": "Bob fills-in and submits the task form",
      "step": "\"Bob\" submits the filled-in form",
      "error": "locator.click: Timeout 30000ms exceeded.",
      "duration": "46.18s"
    },
    {
      "feature": "BPMN",
      "scenario": "Bob inspects the summary task form",
      "step": "\"Bob\" sees that the summary form contains all filled-in data",
      "error": "Error: expect(locator).toHaveValue(expected) failed",
      "duration": "17.28s"
    },
    {
      "feature": "BPMN",
      "scenario": "Bob confirms the data in the summary form",
      "step": "\"Bob\" confirms the data in the form",
      "error": "locator.click: Timeout 30000ms exceeded.",
      "duration": "43.15s"
    }
  ],
  "timestamp": "2026-02-25T21:20:07.245Z"
}